ptmod.py
ptmod-0.0.0.dist-info/LICENSE
ptmod-0.0.0.dist-info/METADATA
ptmod-0.0.0.dist-info/WHEEL
ptmod-0.0.0.dist-info/entry_points.txt
ptmod-0.0.0.dist-info/top_level.txt
ptmod-0.0.0.dist-info/RECORD
