Metadata-Version: 2.1
Name: ptmod
Version: 0.0.0
Summary: A Command line utility to modify serialized PyTorch model states.
Home-page: http://github.com/kamo-naoyuki/ptmod
Author: Naoyuki Kamo
License: MIT
Platform: UNKNOWN
Classifier: Programming Language :: Python
Classifier: Programming Language :: Python :: 3
Classifier: Programming Language :: Python :: 3.6
Classifier: Programming Language :: Python :: 3.7
Requires-Python: >=3.6.0
